Workbook

Sheet 输入假设
A1: 参数 | B1: 单位 | C1: 数值 | D1: 证据/用途
A2: 垃圾体积 | B2: m³ | C2: 2500000 | D2: 测算假设；现行处理量与单价来源S1，其余待核实
A3: 堆积密度 | B3: t/m³ | C3: 0.85 | D3: 测算假设；现行处理量与单价来源S1，其余待核实
A4: 可燃物比例 | B4: % | C4: 0.25 | D4: 测算假设；现行处理量与单价来源S1，其余待核实
A5: 筛下物比例 | B5: % | C5: 0.55 | D5: 测算假设；现行处理量与单价来源S1，其余待核实
A6: 无机物比例 | B6: % | C6: 0.19 | D6: 测算假设；现行处理量与单价来源S1，其余待核实
A7: 金属比例 | B7: % | C7: 0.01 | D7: 测算假设；现行处理量与单价来源S1，其余待核实
A8: 筛下物合规利用比例 | B8: % | C8: 0.6 | D8: 测算假设；现行处理量与单价来源S1，其余待核实
A9: 预处理单价 | B9: 元/m³ | C9: 35 | D9: 测算假设；现行处理量与单价来源S1，其余待核实
A10: 开挖单价 | B10: 元/m³ | C10: 35 | D10: 测算假设；现行处理量与单价来源S1，其余待核实
A11: 筛分运行单价 | B11: 元/t | C11: 80 | D11: 测算假设；现行处理量与单价来源S1，其余待核实
A12: 可燃物外运及处置 | B12: 元/t | C12: 260 | D12: 测算假设；现行处理量与单价来源S1，其余待核实
A13: 筛下物合规利用费用 | B13: 元/t | C13: 60 | D13: 测算假设；现行处理量与单价来源S1，其余待核实
... A48: 其他封场运维假设 | B48: 万元/年 | C48: 150 | D48: 测算假设；现行处理量与单价来源S1，其余待核实

Sheet 治理估算
A1: 费用项目 | B1: 金额（万元） | C1: 计算口径
A2: 调查、勘察、检测与中试 | B2: 800 | C2: 暂列总额；含工程量核实及试开挖
A3: 堆体降液位与好氧预处理 | B3: ='预处理分项'!F9 -> 8750 | C3: 垃圾体积×35元/m³；不含永久地下水治理
A4: 分区开挖与场内短倒 | B4: ='输入假设'!C2*'输入假设'!C10/10000 -> 8750 | C4: 垃圾体积×35元/m³；不含出场运输
A5: 密闭筛分运行 | B5: ='输入假设'!C2*'输入假设'!C3*'输入假设'!C11/10000 -> 17000 | C5: 湿质量×80元/t；含设备租赁及运行，不含车间建造
A6: 可燃物外运及处置 | B6: ='输入假设'!C2*'输入假设'!C3*'输入假设'!C4*'输入假设'!C12/10000 -> 13812.5 | C6: 25%×(运输80+处置180)元/t
A7: 筛下物外运及利用处置 | B7: ='输入假设'!C2*'输入假设'!C3*'输入假设'!C5*('输入假设'!C8*'输入假设'!C13+(1-'输入假设'!C8)*'输入假设'!C14)/10000 -> 16362.5 | C7: 55%×[合规利用率×60+(1−利用率)×260]元/t
A8: 无机惰性物外运及处理 | B8: ='输入假设'!C2*'输入假设'!C3*'输入假设'!C6*'输入假设'!C15/10000 -> 3633.75 | C8: 19%×90元/t；不默认全部可作建材
A9: 金属外运及整理 | B9: ='输入假设'!C2*'输入假设'!C3*'输入假设'!C7*'输入假设'!C16/10000 -> 63.75 | C9: 1%×30元/t；回收销售收入未抵减投资
A10: 模块化密闭设施及集气除臭 | B10: ='密闭除臭分项'!F11 -> 6200 | C10: 车间、可迁移罩棚、防渗地坪及集中除臭，暂列总额
A11: 截排水、调蓄与处理设施升级 | B11: ='水设施分项'!F11 -> 2500 | C11: 含新增300t/d模块、3000m³应急调蓄与300m³浓缩液槽，均待设计询价
A12: 道路、称重、洗车及施工临设 | B12: 1800 | C12: 既有道路升级和临时工程，暂列总额
A13: 施工期渗滤液及浓缩液运行 | B13: ='水运行量价'!F8 -> 9324.125 | C13: 5年现状水＋新增开挖水＋独立积存水假设＋浓缩液；量价展开见专项预算
A14: 基底污染土壤修复 | B14: 2275 | C14: 假设3.5万m³×650元/m³；不含垃圾筛下物
A15: 地下水治理及初期跟踪 | B15: ='地下水分项'!F8 -> 1600 | C15: 暂列总额；不保证地下水在垃圾清场时同步达标
A16: 全过程监测、环保巡查及效果评估 | B16: ='监测分项'!F12 -> 1000 | C16: 井次、点次等量价分解；工程综合监理另在其他费内，避免重复
A17: 直接费用 | B17: =SUM(B2:B16) -> 93871.625 | C17: 费用项完整列示，金额为概念性估算
A18: 工程建设其他费 | B18: =B17*'输入假设'!C17 -> 7509.73 | C18: 费用项完整列示，金额为概念性估算
A19: 基本预备费 | B19: =(B17+B18)*'输入假设'!C18 -> 15207.203 | C19: 费用项完整列示，金额为概念性估算
A20: 治理投资 | B20: =SUM(B17:B19) -> 116588.56 | C20: 费用项完整列示，金额为概念性估算
A21: 产业开发 | B21: ='输入假设'!C19 -> 76800 | C21: 费用项完整列示，金额为概念性估算
A22: 土地取得费 | B22: ='输入假设'!C20 -> 10000 | C22: 费用项完整列示，金额为概念性估算
A23: 建设期利息筹资预算 | B23: ='输入假设'!C21 -> 9500 | C23: 费用项完整列示，金额为概念性估算
A24: 流动资金 | B24: ='输入假设'!C22 -> 3000 | C24: 费用项完整列示，金额为概念性估算
A25: 筹资总需求 | B25: =SUM(B20:B24) -> 215888.56 | C25: 费用项完整列示，金额为概念性估算
A26: 项目评价投资（不含融资利息） | B26: =B25-B23 -> 206388.56 | C26: 费用项完整列示，金额为概念性估算

Sheet 稳态收益与偿债
A1: 项目 | B1: 金额/比率 | C1: 公式说明
A2: 冷链营业收入 | B2: ='输入假设'!C23*'输入假设'!C25*'输入假设'!C27*'输入假设'!C28*365/10000 -> 8376.75 | C2: 万元；DSCR为倍。只看偿债能力，不能替代投资回报评价
A3: 沉香租赁收入 | B3: ='输入假设'!C24*'输入假设'!C26*'输入假设'!C27*'输入假设'!C29*12/10000 -> 979.2 | C3: 万元；DSCR为倍。只看偿债能力，不能替代投资回报评价
A4: 产业服务收入 | B4: ='输入假设'!C30*'输入假设'!C27/0.85 -> 1800 | C4: 万元；DSCR为倍。只看偿债能力，不能替代投资回报评价
A5: 营业收入 | B5: =SUM(B2:B4) -> 11155.95 | C5: 万元；DSCR为倍。只看偿债能力，不能替代投资回报评价
A6: 现金运营支出 | B6: =B2*'输入假设'!C31+B3*'输入假设'!C32+B4*'输入假设'!C33+'输入假设'!C34+'输入假设'!C35 -> 6469.9325 | C6: 万元；DSCR为倍。只看偿债能力，不能替代投资回报评价
A7: EBITDA | B7: =B5-B6 -> 4686.0175 | C7: 万元；DSCR为倍。只看偿债能力，不能替代投资回报评价
A8: 计税折旧 | B8: ='输入假设'!C19/'输入假设'!C37 -> 3840 | C8: 万元；DSCR为倍。只看偿债能力，不能替代投资回报评价
A9: 简化所得税 | B9: =MAX(0,B7-B8)*'输入假设'!C38 -> 211.50437 | C9: 万元；DSCR为倍。只看偿债能力，不能替代投资回报评价
A10: 维护再投入 | B10: ='输入假设'!C36 -> 300 | C10: 万元；DSCR为倍。只看偿债能力，不能替代投资回报评价
A11: 可偿债现金流（CFADS） | B11: =B7-B9-B10 -> 4174.5131 | C11: 万元；DSCR为倍。只看偿债能力，不能替代投资回报评价
A12: 70%贷款本金 | B12: ='治理估算'!B25*'输入假设'!C41 -> 151121.99 | C12: 万元；DSCR为倍。只看偿债能力，不能替代投资回报评价
A13: 等额年本息 | B13: =-PMT('输入假设'!C39,'输入假设'!C40,B12) -> 10633.106 | C13: 万元；DSCR为倍。只看偿债能力，不能替代投资回报评价
A14: 稳态DSCR | B14: =B11/B13 -> 0.39259583 | C14: 万元；DSCR为倍。只看偿债能力，不能替代投资回报评价
A15: 达到DSCR目标的稳态贷款上限 | B15: =B11/'输入假设'!C42/('输入假设'!C39/(1-(1+'输入假设'!C39)^-'输入假设'!C40)) -> 45638.357 | C15: 万元；DSCR为倍。只看偿债能力，不能替代投资回报评价
A16: 资本金及其他非债资金需求 | B16: ='治理估算'!B25-B15 -> 170250.2 | C16: 万元；DSCR为倍。只看偿债能力，不能替代投资回报评价

Sheet 25年项目现金流
A1: 年度 | B1: 建设权重 | C1: 出租率 | D1: 项目投入（不含融资利息） | E1: 冷链收入 | F1: 沉香收入 | G1: 服务收入 | H1: 现金成本 | I1: 折旧 | J1: 所得税 | K1: 维护投入 | L1: 末年残值及流动资金 | M1: 净现金流 | N1: 折现现金流6% | O1: 累计现金流
A2: 0 | B2: 0 | C2: 0 | D2: =-B2*'治理估算'!B26 -> 0 | E2: ='输入假设'!C23*'输入假设'!C25*C2*'输入假设'!C28*365/10000 -> 0 | F2: ='输入假设'!C24*'输入假设'!C26*C2*'输入假设'!C29*12/10000 -> 0 | G2: ='输入假设'!C30*C2/0.85 -> 0 | H2: =IF(A2>5,E2*'输入假设'!C31+F2*'输入假设'!C32+G2*'输入假设'!C33+'输入假设'!C34+'输入假设'!C35,0) -> 0 | I2: =IF(AND(A2>5,A2<=5+'输入假设'!C37),'输入假设'!C19/'输入假设'!C37,0) -> 0 | J2: =MAX(0,SUM(E2:G2)-H2-I2)*'输入假设'!C38 -> 0 | K2: =IF(A2>5,'输入假设'!C36,0) -> 0 | L2: =IF(A2=25,'输入假设'!C19*0.2+'输入假设'!C22,0) -> 0 | M2: =D2+SUM(E2:G2)-H2-J2-K2+L2 -> 0 | N2: =M2/(1+'输入假设'!C43)^A2 -> 0 | O2: =SUM(M$2:M2) -> 0
A3: 1 | B3: 0.1 | C3: 0 | D3: =-B3*'治理估算'!B26 -> -20638.856 | E3: ='输入假设'!C23*'输入假设'!C25*C3*'输入假设'!C28*365/10000 -> 0 | F3: ='输入假设'!C24*'输入假设'!C26*C3*'输入假设'!C29*12/10000 -> 0 | G3: ='输入假设'!C30*C3/0.85 -> 0 | H3: =IF(A3>5,E3*'输入假设'!C31+F3*'输入假设'!C32+G3*'输入假设'!C33+'输入假设'!C34+'输入假设'!C35,0) -> 0 | I3: =IF(AND(A3>5,A3<=5+'输入假设'!C37),'输入假设'!C19/'输入假设'!C37,0) -> 0 | J3: =MAX(0,SUM(E3:G3)-H3-I3)*'输入假设'!C38 -> 0 | K3: =IF(A3>5,'输入假设'!C36,0) -> 0 | L3: =IF(A3=25,'输入假设'!C19*0.2+'输入假设'!C22,0) -> 0 | M3: =D3+SUM(E3:G3)-H3-J3-K3+L3 -> -20638.856 | N3: =M3/(1+'输入假设'!C43)^A3 -> -19470.619 | O3: =SUM(M$2:M3) -> -20638.856
A4: 2 | B4: 0.25 | C4: 0 | D4: =-B4*'治理估算'!B26 -> -51597.14 | E4: ='输入假设'!C23*'输入假设'!C25*C4*'输入假设'!C28*365/10000 -> 0 | F4: ='输入假设'!C24*'输入假设'!C26*C4*'输入假设'!C29*12/10000 -> 0 | G4: ='输入假设'!C30*C4/0.85 -> 0 | H4: =IF(A4>5,E4*'输入假设'!C31+F4*'输入假设'!C32+G4*'输入假设'!C33+'输入假设'!C34+'输入假设'!C35,0) -> 0 | I4: =IF(AND(A4>5,A4<=5+'输入假设'!C37),'输入假设'!C19/'输入假设'!C37,0) -> 0 | J4: =MAX(0,SUM(E4:G4)-H4-I4)*'输入假设'!C38 -> 0 | K4: =IF(A4>5,'输入假设'!C36,0) -> 0 | L4: =IF(A4=25,'输入假设'!C19*0.2+'输入假设'!C22,0) -> 0 | M4: =D4+SUM(E4:G4)-H4-J4-K4+L4 -> -51597.14 | N4: =M4/(1+'输入假设'!C43)^A4 -> -45921.271 | O4: =SUM(M$2:M4) -> -72235.995
A5: 3 | B5: 0.25 | C5: 0 | D5: =-B5*'治理估算'!B26 -> -51597.14 | E5: ='输入假设'!C23*'输入假设'!C25*C5*'输入假设'!C28*365/10000 -> 0 | F5: ='输入假设'!C24*'输入假设'!C26*C5*'输入假设'!C29*12/10000 -> 0 | G5: ='输入假设'!C30*C5/0.85 -> 0 | H5: =IF(A5>5,E5*'输入假设'!C31+F5*'输入假设'!C32+G5*'输入假设'!C33+'输入假设'!C34+'输入假设'!C35,0) -> 0 | I5: =IF(AND(A5>5,A5<=5+'输入假设'!C37),'输入假设'!C19/'输入假设'!C37,0) -> 0 | J5: =MAX(0,SUM(E5:G5)-H5-I5)*'输入假设'!C38 -> 0 | K5: =IF(A5>5,'输入假设'!C36,0) -> 0 | L5: =IF(A5=25,'输入假设'!C19*0.2+'输入假设'!C22,0) -> 0 | M5: =D5+SUM(E5:G5)-H5-J5-K5+L5 -> -51597.14 | N5: =M5/(1+'输入假设'!C43)^A5 -> -43321.953 | O5: =SUM(M$2:M5) -> -123833.13
A6: 4 | B6: 0.25 | C6: 0 | D6: =-B6*'治理估算'!B26 -> -51597.14 | E6: ='输入假设'!C23*'输入假设'!C25*C6*'输入假设'!C28*365/10000 -> 0 | F6: ='输入假设'!C24*'输入假设'!C26*C6*'输入假设'!C29*12/10000 -> 0 | G6: ='输入假设'!C30*C6/0.85 -> 0 | H6: =IF(A6>5,E6*'输入假设'!C31+F6*'输入假设'!C32+G6*'输入假设'!C33+'输入假设'!C34+'输入假设'!C35,0) -> 0 | I6: =IF(AND(A6>5,A6<=5+'输入假设'!C37),'输入假设'!C19/'输入假设'!C37,0) -> 0 | J6: =MAX(0,SUM(E6:G6)-H6-I6)*'输入假设'!C38 -> 0 | K6: =IF(A6>5,'输入假设'!C36,0) -> 0 | L6: =IF(A6=25,'输入假设'!C19*0.2+'输入假设'!C22,0) -> 0 | M6: =D6+SUM(E6:G6)-H6-J6-K6+L6 -> -51597.14 | N6: =M6/(1+'输入假设'!C43)^A6 -> -40869.767 | O6: =SUM(M$2:M6) -> -175430.27
A7: 5 | B7: 0.15 | C7: 0 | D7: =-B7*'治理估算'!B26 -> -30958.284 | E7: ='输入假设'!C23*'输入假设'!C25*C7*'输入假设'!C28*365/10000 -> 0 | F7: ='输入假设'!C24*'输入假设'!C26*C7*'输入假设'!C29*12/10000 -> 0 | G7: ='输入假设'!C30*C7/0.85 -> 0 | H7: =IF(A7>5,E7*'输入假设'!C31+F7*'输入假设'!C32+G7*'输入假设'!C33+'输入假设'!C34+'输入假设'!C35,0) -> 0 | I7: =IF(AND(A7>5,A7<=5+'输入假设'!C37),'输入假设'!C19/'输入假设'!C37,0) -> 0 | J7: =MAX(0,SUM(E7:G7)-H7-I7)*'输入假设'!C38 -> 0 | K7: =IF(A7>5,'输入假设'!C36,0) -> 0 | L7: =IF(A7=25,'输入假设'!C19*0.2+'输入假设'!C22,0) -> 0 | M7: =D7+SUM(E7:G7)-H7-J7-K7+L7 -> -30958.284 | N7: =M7/(1+'输入假设'!C43)^A7 -> -23133.831 | O7: =SUM(M$2:M7) -> -206388.56
A8: 6 | B8: 0 | C8: =MIN('输入假设'!C27,0.6) -> 0.6 | D8: =-B8*'治理估算'!B26 -> 0 | E8: ='输入假设'!C23*'输入假设'!C25*C8*'输入假设'!C28*365/10000 -> 5913 | F8: ='输入假设'!C24*'输入假设'!C26*C8*'输入假设'!C29*12/10000 -> 691.2 | G8: ='输入假设'!C30*C8/0.85 -> 1270.5882 | H8: =IF(A8>5,E8*'输入假设'!C31+F8*'输入假设'!C32+G8*'输入假设'!C33+'输入假设'!C34+'输入假设'!C35,0) -> 4669.9524 | I8: =IF(AND(A8>5,A8<=5+'输入假设'!C37),'输入假设'!C19/'输入假设'!C37,0) -> 3840 | J8: =MAX(0,SUM(E8:G8)-H8-I8)*'输入假设'!C38 -> 0 | K8: =IF(A8>5,'输入假设'!C36,0) -> 300 | L8: =IF(A8=25,'输入假设'!C19*0.2+'输入假设'!C22,0) -> 0 | M8: =D8+SUM(E8:G8)-H8-J8-K8+L8 -> 2904.8359 | N8: =M8/(1+'输入假设'!C43)^A8 -> 2047.7947 | O8: =SUM(M$2:M8) -> -203483.72
A9: 7 | B9: 0 | C9: =MIN('输入假设'!C27,0.75) -> 0.75 | D9: =-B9*'治理估算'!B26 -> 0 | E9: ='输入假设'!C23*'输入假设'!C25*C9*'输入假设'!C28*365/10000 -> 7391.25 | F9: ='输入假设'!C24*'输入假设'!C26*C9*'输入假设'!C29*12/10000 -> 864 | G9: ='输入假设'!C30*C9/0.85 -> 1588.2353 | H9: =IF(A9>5,E9*'输入假设'!C31+F9*'输入假设'!C32+G9*'输入假设'!C33+'输入假设'!C34+'输入假设'!C35,0) -> 5749.9404 | I9: =IF(AND(A9>5,A9<=5+'输入假设'!C37),'输入假设'!C19/'输入假设'!C37,0) -> 3840 | J9: =MAX(0,SUM(E9:G9)-H9-I9)*'输入假设'!C38 -> 63.386213 | K9: =IF(A9>5,'输入假设'!C36,0) -> 300 | L9: =IF(A9=25,'输入假设'!C19*0.2+'输入假设'!C22,0) -> 0 | M9: =D9+SUM(E9:G9)-H9-J9-K9+L9 -> 3730.1586 | N9: =M9/(1+'输入假设'!C43)^A9 -> 2480.7685 | O9: =SUM(M$2:M9) -> -199753.56
A10: 8 | B10: 0 | C10: ='输入假设'!C27 -> 0.85 | D10: =-B10*'治理估算'!B26 -> 0 | E10: ='输入假设'!C23*'输入假设'!C25*C10*'输入假设'!C28*365/10000 -> 8376.75 | F10: ='输入假设'!C24*'输入假设'!C26*C10*'输入假设'!C29*12/10000 -> 979.2 | G10: ='输入假设'!C30*C10/0.85 -> 1800 | H10: =IF(A10>5,E10*'输入假设'!C31+F10*'输入假设'!C32+G10*'输入假设'!C33+'输入假设'!C34+'输入假设'!C35,0) -> 6469.9325 | I10: =IF(AND(A10>5,A10<=5+'输入假设'!C37),'输入假设'!C19/'输入假设'!C37,0) -> 3840 | J10: =MAX(0,SUM(E10:G10)-H10-I10)*'输入假设'!C38 -> 211.50437 | K10: =IF(A10>5,'输入假设'!C36,0) -> 300 | L10: =IF(A10=25,'输入假设'!C19*0.2+'输入假设'!C22,0) -> 0 | M10: =D10+SUM(E10:G10)-H10-J10-K10+L10 -> 4174.5131 | N10: =M10/(1+'输入假设'!C43)^A10 -> 2619.1412 | O10: =SUM(M$2:M10) -> -195579.05
A11: 9 | B11: 0 | C11: ='输入假设'!C27 -> 0.85 | D11: =-B11*'治理估算'!B26 -> 0 | E11: ='输入假设'!C23*'输入假设'!C25*C11*'输入假设'!C28*365/10000 -> 8376.75 | F11: ='输入假设'!C24*'输入假设'!C26*C11*'输入假设'!C29*12/10000 -> 979.2 | G11: ='输入假设'!C30*C11/0.85 -> 1800 | H11: =IF(A11>5,E11*'输入假设'!C31+F11*'输入假设'!C32+G11*'输入假设'!C33+'输入假设'!C34+'输入假设'!C35,0) -> 6469.9325 | I11: =IF(AND(A11>5,A11<=5+'输入假设'!C37),'输入假设'!C19/'输入假设'!C37,0) -> 3840 | J11: =MAX(0,SUM(E11:G11)-H11-I11)*'输入假设'!C38 -> 211.50437 | K11: =IF(A11>5,'输入假设'!C36,0) -> 300 | L11: =IF(A11=25,'输入假设'!C19*0.2+'输入假设'!C22,0) -> 0 | M11: =D11+SUM(E11:G11)-H11-J11-K11+L11 -> 4174.5131 | N11: =M11/(1+'输入假设'!C43)^A11 -> 2470.8879 | O11: =SUM(M$2:M11) -> -191404.54
A12: 10 | B12: 0 | C12: ='输入假设'!C27 -> 0.85 | D12: =-B12*'治理估算'!B26 -> 0 | E12: ='输入假设'!C23*'输入假设'!C25*C12*'输入假设'!C28*365/10000 -> 8376.75 | F12: ='输入假设'!C24*'输入假设'!C26*C12*'输入假设'!C29*12/10000 -> 979.2 | G12: ='输入假设'!C30*C12/0.85 -> 1800 | H12: =IF(A12>5,E12*'输入假设'!C31+F12*'输入假设'!C32+G12*'输入假设'!C33+'输入假设'!C34+'输入假设'!C35,0) -> 6469.9325 | I12: =IF(AND(A12>5,A12<=5+'输入假设'!C37),'输入假设'!C19/'输入假设'!C37,0) -> 3840 | J12: =MAX(0,SUM(E12:G12)-H12-I12)*'输入假设'!C38 -> 211.50437 | K12: =IF(A12>5,'输入假设'!C36,0) -> 300 | L12: =IF(A12=25,'输入假设'!C19*0.2+'输入假设'!C22,0) -> 0 | M12: =D12+SUM(E12:G12)-H12-J12-K12+L12 -> 4174.5131 | N12: =M12/(1+'输入假设'!C43)^A12 -> 2331.0263 | O12: =SUM(M$2:M12) -> -187230.02
A13: 11 | B13: 0 | C13: ='输入假设'!C27 -> 0.85 | D13: =-B13*'治理估算'!B26 -> 0 | E13: ='输入假设'!C23*'输入假设'!C25*C13*'输入假设'!C28*365/10000 -> 8376.75 | F13: ='输入假设'!C24*'输入假设'!C26*C13*'输入假设'!C29*12/10000 -> 979.2 | G13: ='输入假设'!C30*C13/0.85 -> 1800 | H13: =IF(A13>5,E13*'输入假设'!C31+F13*'输入假设'!C32+G13*'输入假设'!C33+'输入假设'!C34+'输入假设'!C35,0) -> 6469.9325 | I13: =IF(AND(A13>5,A13<=5+'输入假设'!C37),'输入假设'!C19/'输入假设'!C37,0) -> 3840 | J13: =MAX(0,SUM(E13:G13)-H13-I13)*'输入假设'!C38 -> 211.50437 | K13: =IF(A13>5,'输入假设'!C36,0) -> 300 | L13: =IF(A13=25,'输入假设'!C19*0.2+'输入假设'!C22,0) -> 0 | M13: =D13+SUM(E13:G13)-H13-J13-K13+L13 -> 4174.5131 | N13: =M13/(1+'输入假设'!C43)^A13 -> 2199.0814 | O13: =SUM(M$2:M13) -> -183055.51
A14: 12 | B14: 0 | C14: ='输入假设'!C27 -> 0.85 | D14: =-B14*'治理估算'!B26 -> 0 | E14: ='输入假设'!C23*'输入假设'!C25*C14*'输入假设'!C28*365/10000 -> 8376.75 | F14: ='输入假设'!C24*'输入假设'!C26*C14*'输入假设'!C29*12/10000 -> 979.2 | G14: ='输入假设'!C30*C14/0.85 -> 1800 | H14: =IF(A14>5,E14*'输入假设'!C31+F14*'输入假设'!C32+G14*'输入假设'!C33+'输入假设'!C34+'输入假设'!C35,0) -> 6469.9325 | I14: =IF(AND(A14>5,A14<=5+'输入假设'!C37),'输入假设'!C19/'输入假设'!C37,0) -> 3840 | J14: =MAX(0,SUM(E14:G14)-H14-I14)*'输入假设'!C38 -> 211.50437 | K14: =IF(A14>5,'输入假设'!C36,0) -> 300 | L14: =IF(A14=25,'输入假设'!C19*0.2+'输入假设'!C22,0) -> 0 | M14: =D14+SUM(E14:G14)-H14-J14-K14+L14 -> 4174.5131 | N14: =M14/(1+'输入假设'!C43)^A14 -> 2074.6051 | O14: =SUM(M$2:M14) -> -178881
A15: 13 | B15: 0 | C15: ='输入假设'!C27 -> 0.85 | D15: =-B15*'治理估算'!B26 -> 0 | E15: ='输入假设'!C23*'输入假设'!C25*C15*'输入假设'!C28*365/10000 -> 8376.75 | F15: ='输入假设'!C24*'输入假设'!C26*C15*'输入假设'!C29*12/10000 -> 979.2 | G15: ='输入假设'!C30*C15/0.85 -> 1800 | H15: =IF(A15>5,E15*'输入假设'!C31+F15*'输入假设'!C32+G15*'输入假设'!C33+'输入假设'!C34+'输入假设'!C35,0) -> 6469.9325 | I15: =IF(AND(A15>5,A15<=5+'输入假设'!C37),'输入假设'!C19/'输入假设'!C37,0) -> 3840 | J15: =MAX(0,SUM(E15:G15)-H15-I15)*'输入假设'!C38 -> 211.50437 | K15: =IF(A15>5,'输入假设'!C36,0) -> 300 | L15: =IF(A15=25,'输入假设'!C19*0.2+'输入假设'!C22,0) -> 0 | M15: =D15+SUM(E15:G15)-H15-J15-K15+L15 -> 4174.5131 | N15: =M15/(1+'输入假设'!C43)^A15 -> 1957.1747 | O15: =SUM(M$2:M15) -> -174706.48
A16: 14 | B16: 0 | C16: ='输入假设'!C27 -> 0.85 | D16: =-B16*'治理估算'!B26 -> 0 | E16: ='输入假设'!C23*'输入假设'!C25*C16*'输入假设'!C28*365/10000 -> 8376.75 | F16: ='输入假设'!C24*'输入假设'!C26*C16*'输入假设'!C29*12/10000 -> 979.2 | G16: ='输入假设'!C30*C16/0.85 -> 1800 | H16: =IF(A16>5,E16*'输入假设'!C31+F16*'输入假设'!C32+G16*'输入假设'!C33+'输入假设'!C34+'输入假设'!C35,0) -> 6469.9325 | I16: =IF(AND(A16>5,A16<=5+'输入假设'!C37),'输入假设'!C19/'输入假设'!C37,0) -> 3840 | J16: =MAX(0,SUM(E16:G16)-H16-I16)*'输入假设'!C38 -> 211.50437 | K16: =IF(A16>5,'输入假设'!C36,0) -> 300 | L16: =IF(A16=25,'输入假设'!C19*0.2+'输入假设'!C22,0) -> 0 | M16: =D16+SUM(E16:G16)-H16-J16-K16+L16 -> 4174.5131 | N16: =M16/(1+'输入假设'!C43)^A16 -> 1846.3912 | O16: =SUM(M$2:M16) -> -170531.97
A17: 15 | B17: 0 | C17: ='输入假设'!C27 -> 0.85 | D17: =-B17*'治理估算'!B26 -> 0 | E17: ='输入假设'!C23*'输入假设'!C25*C17*'输入假设'!C28*365/10000 -> 8376.75 | F17: ='输入假设'!C24*'输入假设'!C26*C17*'输入假设'!C29*12/10000 -> 979.2 | G17: ='输入假设'!C30*C17/0.85 -> 1800 | H17: =IF(A17>5,E17*'输入假设'!C31+F17*'输入假设'!C32+G17*'输入假设'!C33+'输入假设'!C34+'输入假设'!C35,0) -> 6469.9325 | I17: =IF(AND(A17>5,A17<=5+'输入假设'!C37),'输入假设'!C19/'输入假设'!C37,0) -> 3840 | J17: =MAX(0,SUM(E17:G17)-H17-I17)*'输入假设'!C38 -> 211.50437 | K17: =IF(A17>5,'输入假设'!C36,0) -> 300 | L17: =IF(A17=25,'输入假设'!C19*0.2+'输入假设'!C22,0) -> 0 | M17: =D17+SUM(E17:G17)-H17-J17-K17+L17 -> 4174.5131 | N17: =M17/(1+'输入假设'!C43)^A17 -> 1741.8785 | O17: =SUM(M$2:M17) -> -166357.46
A18: 16 | B18: 0 | C18: ='输入假设'!C27 -> 0.85 | D18: =-B18*'治理估算'!B26 -> 0 | E18: ='输入假设'!C23*'输入假设'!C25*C18*'输入假设'!C28*365/10000 -> 8376.75 | F18: ='输入假设'!C24*'输入假设'!C26*C18*'输入假设'!C29*12/10000 -> 979.2 | G18: ='输入假设'!C30*C18/0.85 -> 1800 | H18: =IF(A18>5,E18*'输入假设'!C31+F18*'输入假设'!C32+G18*'输入假设'!C33+'输入假设'!C34+'输入假设'!C35,0) -> 6469.9325 | I18: =IF(AND(A18>5,A18<=5+'输入假设'!C37),'输入假设'!C19/'输入假设'!C37,0) -> 3840 | J18: =MAX(0,SUM(E18:G18)-H18-I18)*'输入假设'!C38 -> 211.50437 | K18: =IF(A18>5,'输入假设'!C36,0) -> 300 | L18: =IF(A18=25,'输入假设'!C19*0.2+'输入假设'!C22,0) -> 0 | M18: =D18+SUM(E18:G18)-H18-J18-K18+L18 -> 4174.5131 | N18: =M18/(1+'输入假设'!C43)^A18 -> 1643.2816 | O18: =SUM(M$2:M18) -> -162182.95
A19: 17 | B19: 0 | C19: ='输入假设'!C27 -> 0.85 | D19: =-B19*'治理估算'!B26 -> 0 | E19: ='输入假设'!C23*'输入假设'!C25*C19*'输入假设'!C28*365/10000 -> 8376.75 | F19: ='输入假设'!C24*'输入假设'!C26*C19*'输入假设'!C29*12/10000 -> 979.2 | G19: ='输入假设'!C30*C19/0.85 -> 1800 | H19: =IF(A19>5,E19*'输入假设'!C31+F19*'输入假设'!C32+G19*'输入假设'!C33+'输入假设'!C34+'输入假设'!C35,0) -> 6469.9325 | I19: =IF(AND(A19>5,A19<=5+'输入假设'!C37),'输入假设'!C19/'输入假设'!C37,0) -> 3840 | J19: =MAX(0,SUM(E19:G19)-H19-I19)*'输入假设'!C38 -> 211.50437 | K19: =IF(A19>5,'输入假设'!C36,0) -> 300 | L19: =IF(A19=25,'输入假设'!C19*0.2+'输入假设'!C22,0) -> 0 | M19: =D19+SUM(E19:G19)-H19-J19-K19+L19 -> 4174.5131 | N19: =M19/(1+'输入假设'!C43)^A19 -> 1550.2656 | O19: =SUM(M$2:M19) -> -158008.43
A20: 18 | B20: 0 | C20: ='输入假设'!C27 -> 0.85 | D20: =-B20*'治理估算'!B26 -> 0 | E20: ='输入假设'!C23*'输入假设'!C25*C20*'输入假设'!C28*365/10000 -> 8376.75 | F20: ='输入假设'!C24*'输入假设'!C26*C20*'输入假设'!C29*12/10000 -> 979.2 | G20: ='输入假设'!C30*C20/0.85 -> 1800 | H20: =IF(A20>5,E20*'输入假设'!C31+F20*'输入假设'!C32+G20*'输入假设'!C33+'输入假设'!C34+'输入假设'!C35,0) -> 6469.9325 | I20: =IF(AND(A20>5,A20<=5+'输入假设'!C37),'输入假设'!C19/'输入假设'!C37,0) -> 3840 | J20: =MAX(0,SUM(E20:G20)-H20-I20)*'输入假设'!C38 -> 211.50437 | K20: =IF(A20>5,'输入假设'!C36,0) -> 300 | L20: =IF(A20=25,'输入假设'!C19*0.2+'输入假设'!C22,0) -> 0 | M20: =D20+SUM(E20:G20)-H20-J20-K20+L20 -> 4174.5131 | N20: =M20/(1+'输入假设'!C43)^A20 -> 1462.5148 | O20: =SUM(M$2:M20) -> -153833.92
A21: 19 | B21: 0 | C21: ='输入假设'!C27 -> 0.85 | D21: =-B21*'治理估算'!B26 -> 0 | E21: ='输入假设'!C23*'输入假设'!C25*C21*'输入假设'!C28*365/10000 -> 8376.75 | F21: ='输入假设'!C24*'输入假设'!C26*C21*'输入假设'!C29*12/10000 -> 979.2 | G21: ='输入假设'!C30*C21/0.85 -> 1800 | H21: =IF(A21>5,E21*'输入假设'!C31+F21*'输入假设'!C32+G21*'输入假设'!C33+'输入假设'!C34+'输入假设'!C35,0) -> 6469.9325 | I21: =IF(AND(A21>5,A21<=5+'输入假设'!C37),'输入假设'!C19/'输入假设'!C37,0) -> 3840 | J21: =MAX(0,SUM(E21:G21)-H21-I21)*'输入假设'!C38 -> 211.50437 | K21: =IF(A21>5,'输入假设'!C36,0) -> 300 | L21: =IF(A21=25,'输入假设'!C19*0.2+'输入假设'!C22,0) -> 0 | M21: =D21+SUM(E21:G21)-H21-J21-K21+L21 -> 4174.5131 | N21: =M21/(1+'输入假设'!C43)^A21 -> 1379.7309 | O21: =SUM(M$2:M21) -> -149659.41
A22: 20 | B22: 0 | C22: ='输入假设'!C27 -> 0.85 | D22: =-B22*'治理估算'!B26 -> 0 | E22: ='输入假设'!C23*'输入假设'!C25*C22*'输入假设'!C28*365/10000 -> 8376.75 | F22: ='输入假设'!C24*'输入假设'!C26*C22*'输入假设'!C29*12/10000 -> 979.2 | G22: ='输入假设'!C30*C22/0.85 -> 1800 | H22: =IF(A22>5,E22*'输入假设'!C31+F22*'输入假设'!C32+G22*'输入假设'!C33+'输入假设'!C34+'输入假设'!C35,0) -> 6469.9325 | I22: =IF(AND(A22>5,A22<=5+'输入假设'!C37),'输入假设'!C19/'输入假设'!C37,0) -> 3840 | J22: =MAX(0,SUM(E22:G22)-H22-I22)*'输入假设'!C38 -> 211.50437 | K22: =IF(A22>5,'输入假设'!C36,0) -> 300 | L22: =IF(A22=25,'输入假设'!C19*0.2+'输入假设'!C22,0) -> 0 | M22: =D22+SUM(E22:G22)-H22-J22-K22+L22 -> 4174.5131 | N22: =M22/(1+'输入假设'!C43)^A22 -> 1301.6329 | O22: =SUM(M$2:M22) -> -145484.89
A23: 21 | B23: 0 | C23: ='输入假设'!C27 -> 0.85 | D23: =-B23*'治理估算'!B26 -> 0 | E23: ='输入假设'!C23*'输入假设'!C25*C23*'输入假设'!C28*365/10000 -> 8376.75 | F23: ='输入假设'!C24*'输入假设'!C26*C23*'输入假设'!C29*12/10000 -> 979.2 | G23: ='输入假设'!C30*C23/0.85 -> 1800 | H23: =IF(A23>5,E23*'输入假设'!C31+F23*'输入假设'!C32+G23*'输入假设'!C33+'输入假设'!C34+'输入假设'!C35,0) -> 6469.9325 | I23: =IF(AND(A23>5,A23<=5+'输入假设'!C37),'输入假设'!C19/'输入假设'!C37,0) -> 3840 | J23: =MAX(0,SUM(E23:G23)-H23-I23)*'输入假设'!C38 -> 211.50437 | K23: =IF(A23>5,'输入假设'!C36,0) -> 300 | L23: =IF(A23=25,'输入假设'!C19*0.2+'输入假设'!C22,0) -> 0 | M23: =D23+SUM(E23:G23)-H23-J23-K23+L23 -> 4174.5131 | N23: =M23/(1+'输入假设'!C43)^A23 -> 1227.9556 | O23: =SUM(M$2:M23) -> -141310.38
A24: 22 | B24: 0 | C24: ='输入假设'!C27 -> 0.85 | D24: =-B24*'治理估算'!B26 -> 0 | E24: ='输入假设'!C23*'输入假设'!C25*C24*'输入假设'!C28*365/10000 -> 8376.75 | F24: ='输入假设'!C24*'输入假设'!C26*C24*'输入假设'!C29*12/10000 -> 979.2 | G24: ='输入假设'!C30*C24/0.85 -> 1800 | H24: =IF(A24>5,E24*'输入假设'!C31+F24*'输入假设'!C32+G24*'输入假设'!C33+'输入假设'!C34+'输入假设'!C35,0) -> 6469.9325 | I24: =IF(AND(A24>5,A24<=5+'输入假设'!C37),'输入假设'!C19/'输入假设'!C37,0) -> 3840 | J24: =MAX(0,SUM(E24:G24)-H24-I24)*'输入假设'!C38 -> 211.50437 | K24: =IF(A24>5,'输入假设'!C36,0) -> 300 | L24: =IF(A24=25,'输入假设'!C19*0.2+'输入假设'!C22,0) -> 0 | M24: =D24+SUM(E24:G24)-H24-J24-K24+L24 -> 4174.5131 | N24: =M24/(1+'输入假设'!C43)^A24 -> 1158.4487 | O24: =SUM(M$2:M24) -> -137135.87
A25: 23 | B25: 0 | C25: ='输入假设'!C27 -> 0.85 | D25: =-B25*'治理估算'!B26 -> 0 | E25: ='输入假设'!C23*'输入假设'!C25*C25*'输入假设'!C28*365/10000 -> 8376.75 | F25: ='输入假设'!C24*'输入假设'!C26*C25*'输入假设'!C29*12/10000 -> 979.2 | G25: ='输入假设'!C30*C25/0.85 -> 1800 | H25: =IF(A25>5,E25*'输入假设'!C31+F25*'输入假设'!C32+G25*'输入假设'!C33+'输入假设'!C34+'输入假设'!C35,0) -> 6469.9325 | I25: =IF(AND(A25>5,A25<=5+'输入假设'!C37),'输入假设'!C19/'输入假设'!C37,0) -> 3840 | J25: =MAX(0,SUM(E25:G25)-H25-I25)*'输入假设'!C38 -> 211.50437 | K25: =IF(A25>5,'输入假设'!C36,0) -> 300 | L25: =IF(A25=25,'输入假设'!C19*0.2+'输入假设'!C22,0) -> 0 | M25: =D25+SUM(E25:G25)-H25-J25-K25+L25 -> 4174.5131 | N25: =M25/(1+'输入假设'!C43)^A25 -> 1092.8761 | O25: =SUM(M$2:M25) -> -132961.35
A26: 24 | B26: 0 | C26: ='输入假设'!C27 -> 0.85 | D26: =-B26*'治理估算'!B26 -> 0 | E26: ='输入假设'!C23*'输入假设'!C25*C26*'输入假设'!C28*365/10000 -> 8376.75 | F26: ='输入假设'!C24*'输入假设'!C26*C26*'输入假设'!C29*12/10000 -> 979.2 | G26: ='输入假设'!C30*C26/0.85 -> 1800 | H26: =IF(A26>5,E26*'输入假设'!C31+F26*'输入假设'!C32+G26*'输入假设'!C33+'输入假设'!C34+'输入假设'!C35,0) -> 6469.9325 | I26: =IF(AND(A26>5,A26<=5+'输入假设'!C37),'输入假设'!C19/'输入假设'!C37,0) -> 3840 | J26: =MAX(0,SUM(E26:G26)-H26-I26)*'输入假设'!C38 -> 211.50437 | K26: =IF(A26>5,'输入假设'!C36,0) -> 300 | L26: =IF(A26=25,'输入假设'!C19*0.2+'输入假设'!C22,0) -> 0 | M26: =D26+SUM(E26:G26)-H26-J26-K26+L26 -> 4174.5131 | N26: =M26/(1+'输入假设'!C43)^A26 -> 1031.0152 | O26: =SUM(M$2:M26) -> -128786.84
A27: 25 | B27: 0 | C27: ='输入假设'!C27 -> 0.85 | D27: =-B27*'治理估算'!B26 -> 0 | E27: ='输入假设'!C23*'输入假设'!C25*C27*'输入假设'!C28*365/10000 -> 8376.75 | F27: ='输入假设'!C24*'输入假设'!C26*C27*'输入假设'!C29*12/10000 -> 979.2 | G27: ='输入假设'!C30*C27/0.85 -> 1800 | H27: =IF(A27>5,E27*'输入假设'!C31+F27*'输入假设'!C32+G27*'输入假设'!C33+'输入假设'!C34+'输入假设'!C35,0) -> 6469.9325 | I27: =IF(AND(A27>5,A27<=5+'输入假设'!C37),'输入假设'!C19/'输入假设'!C37,0) -> 3840 | J27: =MAX(0,SUM(E27:G27)-H27-I27)*'输入假设'!C38 -> 211.50437 | K27: =IF(A27>5,'输入假设'!C36,0) -> 300 | L27: =IF(A27=25,'输入假设'!C19*0.2+'输入假设'!C22,0) -> 18360 | M27: =D27+SUM(E27:G27)-H27-J27-K27+L27 -> 22534.513 | N27: =M27/(1+'输入假设'!C43)^A27 -> 5250.5107 | O27: =SUM(M$2:M27) -> -106252.33
A28: 项目FIRR | B28: =IRR(M2:M27) -> -0.046562083
A29: FNPV6% | B29: =SUM(N2:N27) -> -133850.46

Sheet 情景及校核值
A1: 指标 | B1: 测算数值 | C1: 单位/备注
A2: 小体量治理投资 | B2: 89414.592 | C2: 万元；情景参数见报告
A3: 小体量筹资总需求 | B3: 188714.59 | C3: 万元
A4: 基准治理投资 | B4: 116588.56 | C4: 万元；情景参数见报告
A5: 基准筹资总需求 | B5: 215888.56 | C5: 万元
A6: 大体量治理投资 | B6: 119985.3 | C6: 万元；情景参数见报告
A7: 大体量筹资总需求 | B7: 219285.3 | C7: 万元
A8: 压力治理投资 | B8: 164940.86 | C8: 万元；情景参数见报告
A9: 压力筹资总需求 | B9: 264240.86 | C9: 万元
A10: 稳态营业收入 | B10: 11155.95 | C10: 当前基准校核值，本次基准静态校核值；修改后以公式页重算结果为准
A11: 稳态CFADS | B11: 4174.5131 | C11: 当前基准校核值，本次基准静态校核值；修改后以公式页重算结果为准
A12: 70%贷款稳态DSCR | B12: 0.39259583 | C12: 当前基准校核值，本次基准静态校核值；修改后以公式页重算结果为准
A13: 首个运营年DSCR | B13: 0.2731879 | C13: 当前基准校核值，本次基准静态校核值；修改后以公式页重算结果为准
... A21: 20年避免费用现值4.5% | B21: 12130.876 | C21: 当前基准校核值，本次基准静态校核值；修改后以公式页重算结果为准

Sheet 说明与证据
A1: 事项 | B1: 说明
A2: 定位 | B2: 概念阶段可研测算工作簿，非批复概算、招标控制价或银行授信承诺。所有价格待询价。
A3: 垃圾体积 | B3: 250万m³优先取S1场地整治扫描件第1页；170/260万m³作为附件冲突情景。
A4: 基准成本 | B4: 35元/m³等均为建模假设；密闭设施固定投资与筛分运行费用分开计，不抵减废料收入。
A5: 金融口径 | B5: 筹资需求含建设期利息；项目FIRR/FNPV剔除该融资利息，避免项目评价重复计息。
A6: 税费口径 | B6: 收入为不含增值税概念口径，所得税简化按EBITDA扣产业折旧25%；附加税、土地税、土地摊销等未精算，正式可研必须重算。
A7: 收入限制 | B7: 不计土地出让、税收返还、政府运营付费、财政运维节省、未知补贴和未经落实碳收益。
A8: 偿债上限 | B8: 20年3.5%等额年本息假设，DSCR阈值1.30为审慎模型值，非监管统一硬线；爬坡期另算。
A9: 审计状态 | B9: 数值校核页由同一模型计算；公式页请用Excel打开自动重算。开启了自动计算。
A10: 资本金意义 | B10: 贷款比例降低只能改善偿债覆盖，不能把负项目净现值转为正值。
A11: 网络核验 | B11: 玉龙案例仅附件线索；本轮外网检索受环境白名单限制，未独立证实官方最新投资及进度。
A12: 污染防治深化修订 | B12: 水运行由3000暂列改为9324.125万元量价情景；初始4万吨与价格均待实测询价；分项预算在治理总额中分解，不重复相加。
A13: 污染防治深化修订 | B13: 水运行由3000暂列改为9324.125万元量价情景；初始4万吨与价格均待实测询价；分项预算在治理总额中分解，不重复相加。

Sheet 密闭除臭分项
A1: 设施/工作 | B1: 数量 | C1: 数量单位 | D1: 单价 | E1: 单价单位 | F1: 金额（万元）
A2: 密闭筛分车间 | B2: 8000 | C2: m² | D2: 1800 | E2: 元/m² | F2: =B2*D2/10000 -> 1440
A3: 防雨防渗分仓暂存区 | B3: 20000 | C3: m² | D3: 600 | E3: 元/m² | F3: =B3*D3/10000 -> 1200
A4: 可迁移开挖罩棚 | B4: 3 | C4: 套 | D4: 240 | E4: 万元/套 | F4: =B4*D4 -> 720
A5: 集中集气净化除臭单元 | B5: 2 | C5: 套 | D5: 900 | E5: 万元/套 | F5: =B5*D5 -> 1800
A6: 喷雾抑尘及消杀系统 | B6: 5 | C6: 套 | D6: 30 | E6: 万元/套 | F6: =B6*D6 -> 150
A7: 连续气体与气象检测 | B7: 10 | C7: 组 | D7: 12 | E7: 万元/组 | F7: =B7*D7 -> 120
A8: 输送卸料局部密闭集气 | B8: 3 | C8: 组 | D8: 60 | E8: 万元/组 | F8: =B8*D8 -> 180
A9: 防爆电气、消防与应急保障 | B9: 1 | C9: 项 | D9: 290 | E9: 万元/项 | F9: =B9*D9 -> 290
A10: 集气管网阀门与备用风机 | B10: 1 | C10: 项 | D10: 300 | E10: 万元/项 | F10: =B10*D10 -> 300
A11: 合计 | F11: =SUM(F2:F10) -> 6200

Sheet 水设施分项
A1: 设施/工作 | B1: 数量 | C1: 数量单位 | D1: 单价 | E1: 单价单位 | F1: 金额（万元）
A2: 现有池清淤修缮与防渗复核 | B2: 2 | C2: 设施 | D2: 180 | E2: 万元/设施 | F2: =B2*D2 -> 360
A3: 新增分格应急调蓄池 | B3: 3000 | C3: m³ | D3: 900 | E3: 元/m³ | F3: =B3*D3/10000 -> 270
A4: 新增水处理模块 | B4: 300 | C4: t/d | D4: 35000 | E4: 元/(t/d) | F4: =B4*D4/10000 -> 1050
A5: 截排水管沟、盲沟与泵组 | B5: 1200 | C5: m | D5: 2500 | E5: 元/m | F5: =B5*D5/10000 -> 300
A6: 泵电与应急设施 | B6: 1 | C6: 项 | D6: 120 | E6: 万元/项 | F6: =B6*D6 -> 120
A7: 独立浓缩液贮槽 | B7: 300 | C7: m³ | D7: 4500 | E7: 元/m³ | F7: =B7*D7/10000 -> 135
A8: 流量、液位与报警 | B8: 1 | C8: 项 | D8: 80 | E8: 万元/项 | F8: =B8*D8 -> 80
A9: 均质及预处理完善 | B9: 1 | C9: 项 | D9: 160 | E9: 万元/项 | F9: =B9*D9 -> 160
A10: 水质试验及调试 | B10: 1 | C10: 项 | D10: 25 | E10: 万元/项 | F10: =B10*D10 -> 25
A11: 合计 | F11: =SUM(F2:F10) -> 2500

Sheet 监测分项
A1: 设施/工作 | B1: 数量 | C1: 数量单位 | D1: 单价 | E1: 单价单位 | F1: 金额（万元）
A2: 地下水 | B2: 1560 | C2: 井次 | D2: 1800 | E2: 元/井次 | F2: =B2*D2/10000 -> 280.8
A3: 地表水 | B3: 780 | C3: 断面次 | D3: 900 | E3: 元/断面次 | F3: =B3*D3/10000 -> 70.2
A4: 场界与敏感点气味颗粒物 | B4: 360 | C4: 点次 | D4: 2500 | E4: 元/点次 | F4: =B4*D4/10000 -> 90
A5: 有组织废气 | B5: 120 | C5: 口次 | D5: 3500 | E5: 元/口次 | F5: =B5*D5/10000 -> 42
A6: 渗滤液/出水/浓缩液 | B6: 180 | C6: 点次 | D6: 3000 | E6: 元/点次 | F6: =B6*D6/10000 -> 54
A7: 噪声 | B7: 240 | C7: 点次 | D7: 500 | E7: 元/点次 | F7: =B7*D7/10000 -> 12
A8: 产物验证性CMA检测 | B8: 240 | C8: 组 | D8: 4500 | E8: 元/组 | F8: =B8*D8/10000 -> 108
A9: 独立治理效果评估 | B9: 1 | C9: 项 | D9: 90 | E9: 万元/项 | F9: =B9*D9 -> 90
A10: 环保专项巡查与联单审查 | B10: 1 | C10: 项 | D10: 153 | E10: 万元/项 | F10: =B10*D10 -> 153
A11: 仪表校准及数据质量维护 | B11: 1 | C11: 项 | D11: 100 | E11: 万元/项 | F11: =B11*D11 -> 100
A12: 合计 | F12: =SUM(F2:F11) -> 1000

Sheet 地下水分项
A1: 设施/工作 | B1: 数量 | C1: 数量单位 | D1: 单价 | E1: 单价单位 | F1: 金额（万元）
A2: 井网补建及水文试验 | B2: 8 | C2: 井 | D2: 15 | E2: 万元/井 | F2: =B2*D2 -> 120
A3: 拦截抽提井泵系统 | B3: 4 | C3: 套 | D3: 60 | E3: 万元/套 | F3: =B3*D3 -> 240
A4: 独立地下水处理设施 | B4: 100 | C4: t/d | D4: 40000 | E4: 元/(t/d) | F4: =B4*D4/10000 -> 400
A5: 屏障/原位措施试验与实施 | B5: 1 | C5: 项 | D5: 260 | E5: 万元/项 | F5: =B5*D5 -> 260
A6: 初期治理运维 | B6: 5 | C6: 年 | D6: 80 | E6: 万元/年 | F6: =B6*D6 -> 400
A7: 配套泵管、供电与控制 | B7: 1 | C7: 项 | D7: 180 | E7: 万元/项 | F7: =B7*D7 -> 180
A8: 合计 | F8: =SUM(F2:F7) -> 1600

Sheet 预处理分项
A1: 设施/工作 | B1: 数量 | C1: 数量单位 | D1: 单价 | E1: 单价单位 | F1: 金额（万元）
A2: 堆体降液位井泵与抽排 | B2: 1 | C2: 项 | D2: 1700 | E2: 万元/项 | F2: =B2*D2 -> 1700
A3: 好氧抽注井及管网 | B3: 1 | C3: 项 | D3: 2600 | E3: 万元/项 | F3: =B3*D3 -> 2600
A4: 可移动抽注气机组 | B4: 1 | C4: 项 | D4: 1600 | E4: 万元/项 | F4: =B4*D4 -> 1600
A5: 气水温专项控制 | B5: 1 | C5: 项 | D5: 600 | E5: 万元/项 | F5: =B5*D5 -> 600
A6: 预处理电耗人工及耗材 | B6: 1 | C6: 项 | D6: 1500 | E6: 万元/项 | F6: =B6*D6 -> 1500
A7: 井口封闭与膜面恢复 | B7: 1 | C7: 项 | D7: 600 | E7: 万元/项 | F7: =B7*D7 -> 600
A8: 符合燃烧条件时的安全气体处理 | B8: 1 | C8: 项 | D8: 150 | E8: 万元/项 | F8: =B8*D8 -> 150
A9: 合计 | F9: =SUM(F2:F8) -> 8750

Sheet 水运行量价
A1: 费用 | B1: 数量（t） | C1: 量价假设 | D1: 单价（元/t） | E1: 责任说明 | F1: 金额（万元）
A2: 现状渗滤液 | B2: 310250 | C2: 5年×365天×170t/d | D2: 115 | E2: 主体及真实合同核定 | F2: =B2*D2/10000 -> 3567.875
A3: 新增开挖水 | B3: 171875 | C3: 33月×250工作日/年×250t/d | D3: 160 | E3: 主体及真实合同核定 | F3: =B3*D3/10000 -> 2750
A4: 额外积存水 | B4: 40000 | C4: 待实测且与现状流量分离 | D4: 160 | E4: 主体及真实合同核定 | F4: =B4*D4/10000 -> 640
A5: 现状浓缩液 | B5: 36500 | C5: 5年×365天×20t/d | D5: 300 | E5: 主体及真实合同核定 | F5: =B5*D5/10000 -> 1095
A6: 新增浓缩液 | B6: 34375 | C6: 新增水×20% | D6: 300 | E6: 主体及真实合同核定 | F6: =B6*D6/10000 -> 1031.25
A7: 积存水浓缩液 | B7: 8000 | C7: 积存水×20% | D7: 300 | E7: 主体及真实合同核定 | F7: =B7*D7/10000 -> 240
A8: 合计 | F8: =SUM(F2:F7) -> 9324.125
